{"stats":{"minecraft:broken":{"iceandfire:armor_blue_helmet":1,"minecraft:iron_leggings":1,"minecraft:wooden_pickaxe":1,"simplyswords:iron_scythe":1,"minecraft:shield":1,"minecraft:iron_helmet":1,"iceandfire:armor_amythest_boots":1,"minecraft:diamond_boots":1,"minecraft:golden_hoe":1,"iceandfire:armor_amythest_helmet":1,"iceandfire:armor_copper_metal_boots":1},"minecraft:dropped":{"minecraft:iron_sword":2,"iceandfire:raw_silver":2,"block_factorys_bosses:prison_door":1,"knightlib:small_essence":62,"minecraft:porkchop":1,"irons_spellbooks:rare_ink":2,"minecraft:glow_ink_sac":3,"minecraft:glass_bottle":10,"minecraft:diamond":3,"minecraft:cooked_porkchop":6,"artifacts:shock_pendant":1,"minecraft:crossbow":3,"simplyswords:iron_halberd":1,"minecraft:saddle":1,"block_factorys_bosses:tall_vase":1,"irons_spellbooks:tarnished_helmet":1,"artifacts:universal_attractor":1,"minecraft:emerald":18,"minecraft:gold_block":2,"minecraft:dirt":71,"minecraft:grass":1,"irons_spellbooks:silver_ring":2,"minecraft:stone_button":6,"create:scorchia":38,"relics:aqua_walker":1,"irons_spellbooks:epic_ink":2,"artifacts:charm_of_sinking":1,"irons_spellbooks:arcane_essence":49,"minecraft:writable_book":1,"minecraft:sunflower":5,"minecraft:phantom_membrane":4,"minecraft:iron_pickaxe":3,"minecraft:sugar":2,"minecraft:white_wool":7,"minecraft:diorite_slab":1,"minecraft:bone":89,"minecraft:stone_axe":1,"minecraft:sugar_cane":3,"irons_spellbooks:blank_rune":1,"alexsmobs:gazelle_horn":1,"minecraft:iron_nugget":6,"minecraft:cobbled_deepslate":57,"relics:drowned_belt":1,"alexscaves:cave_tablet":16,"minecraft:wheat":34,"minecraft:obsidian":11,"minecraft:rotten_flesh":95,"simplyswords:diamond_twinblade":1,"minecraft:azure_bluet":20,"irons_spellbooks:inscription_table":1,"iceandfire:crackled_gravel":2,"iceandfire:shiny_scales":3,"alexsmobs:blood_sac":6,"minecraft:tipped_arrow":2,"minecraft:charcoal":2,"irons_spellbooks:cooldown_ring":1,"iceandfire:bestiary":1,"create:limestone":2,"minecraft:acacia_sapling":1,"minecraft:beef":4,"minecraft:acacia_fence":1,"iceandfire:manuscript":65,"irons_spellbooks:poisonward_ring":1,"minecraft:enchanted_book":2,"minecraft:iron_ingot":90,"irons_spellbooks:divine_pearl":9,"minecraft:wheat_seeds":164,"minecraft:cobbled_deepslate_stairs":1,"minecraft:tnt":3,"minecraft:feather":9,"minecraft:iron_helmet":2,"minecraft:cobblestone":86,"minecraft:book":2,"minecraft:apple":1,"iceandfire:armor_blue_boots":1,"minecraft:coal":1,"minecraft:golden_apple":2,"minecraft:oxeye_daisy":2,"iceandfire:deathworm_chitin_red":1,"relics:roller_skates":2,"iceandfire:copper_nugget":82,"knightlib:great_essence":38,"minecraft:cooked_salmon":1,"minecraft:diamond_helmet":1,"simplyswords:frostfall":17,"minecraft:potion":2,"minecraft:white_banner":3,"minecraft:paper":86,"minecraft:string":38,"irons_spellbooks:nature_rune":1,"minecraft:acacia_planks":5,"iceandfire:dragon_skull_fire":1,"minecraft:spruce_sapling":14,"minecraft:pink_tulip":3,"iceandfire:silver_nugget":66,"minecraft:furnace":1,"minecraft:moss_carpet":3,"minecraft:stone_sword":1,"irons_spellbooks:uncommon_ink":1,"iceandfire:troll_leather_forest":6,"minecraft:iron_boots":2,"iceandfire:dragon_skull_ice":3,"alexsmobs:cooked_kangaroo_meat":1,"iceandfire:dragon_ice":1,"minecraft:spruce_boat":3,"minecraft:hay_block":28,"minecraft:spruce_planks":9,"minecraft:diamond_pickaxe":4,"artifacts:eternal_steak":2,"minecraft:stone_pressure_plate":1,"minecraft:spider_eye":12,"minecraft:stone_bricks":12,"minecraft:bamboo":64,"minecraft:bow":7,"iceandfire:dragonbone_sword_lightning":4,"minecraft:bell":1,"minecraft:cyan_bed":6,"iceandfire:dragon_skull_lightning":5,"simplyswords:iron_claymore":2,"minecraft:black_wool":1,"irons_spellbooks:concentration_amulet":1,"minecraft:oak_log":2,"minecraft:ender_pearl":3,"block_factorys_bosses:bone_remains_legs":2,"iceandfire:ice_dragon_flesh":3,"iceandfire:fire_dragon_flesh":7,"minecraft:lantern":6,"minecraft:leather":1,"travelersbackpack:standard":1,"minecraft:flint":1,"minecraft:cyan_terracotta":17,"minecraft:cracked_polished_blackstone_bricks":32,"minecraft:polished_blackstone_brick_stairs":3,"irons_spellbooks:hogskin":2,"minecraft:cornflower":4,"minecraft:mutton":2,"minecraft:crimson_roots":5,"minecraft:snowball":123,"iceandfire:chared_gravel":1,"iceandfire:dragonscales_red":5,"gravestone:obituary":64,"minecraft:amethyst_shard":4,"iceandfire:ash":2,"minecraft:polished_blackstone_bricks":41,"irons_spellbooks:emerald_stoneplate_ring":1,"minecraft:gold_ingot":44,"minecraft:gravel":8,"minecraft:white_tulip":2,"hangglider:glider_framework":1,"minecraft:blackstone":42,"hangglider:hang_glider":4,"minecraft:mangrove_roots":1,"iceandfire:frozen_stone":2,"minecraft:mossy_stone_brick_slab":2,"minecraft:cooked_mutton":2,"irons_spellbooks:invisibility_elixir":1,"alexsmobs:kangaroo_hide":10,"minecraft:poppy":3,"minecraft:gunpowder":13,"minecraft:azalea":2,"minecraft:basalt":17,"minecraft:arrow":43,"iceandfire:armor_copper_metal_leggings":3,"minecraft:netherrack":209,"simplyswords:gold_halberd":4,"minecraft:purple_carpet":1,"minecraft:bread":135,"iceandfire:lightning_dragon_blood":1,"irons_spellbooks:legendary_ink":3,"travelersbackpack:bookshelf":3,"minecraft:mossy_cobblestone":2,"minecraft:golden_axe":1,"minecraft:amethyst_block":11,"minecraft:spruce_stairs":1,"block_factorys_bosses:ancient_iron_ingot":2,"minecraft:acacia_log":2,"minecraft:magenta_bed":1,"minecraft:stick":12,"irons_spellbooks:scroll":13,"block_factorys_bosses:bone_remains":2,"minecraft:brewing_stand":1,"minecraft:torch":3,"minecraft:nether_wart_block":1,"block_factorys_bosses:ancient_iron_nugget":1,"minecraft:iron_leggings":1,"minecraft:green_carpet":3,"iceandfire:armor_white_leggings":1,"irons_spellbooks:common_ink":1,"minecraft:iron_axe":1,"artifacts:feral_claws":1,"minecraft:pink_petals":3,"irons_spellbooks:frozen_bone":5,"minecraft:bucket":1,"block_factorys_bosses:knight_helmet":1,"minecraft:dandelion":5,"iceandfire:dragonbone":33,"minecraft:smooth_basalt":11,"minecraft:redstone":1,"alexsmobs:maggot":4,"minecraft:sweet_berries":16,"minecraft:oak_trapdoor":2,"iceandfire:armor_blue_chestplate":3,"block_factorys_bosses:vase":1,"minecraft:raw_iron":10,"block_factorys_bosses:wall_torch":1,"minecraft:iron_hoe":1,"minecraft:flint_and_steel":3,"irons_spellbooks:frostward_ring":1,"simplyswords:iron_scythe":4,"minecraft:shield":1,"iceandfire:armor_green_boots":1,"iceandfire:dragonscales_amythest":2,"minecraft:iron_chestplate":2,"minecraft:spruce_log":63,"iceandfire:fire_dragon_heart":1,"minecraft:stone_pickaxe":2,"simplyswords:diamond_scythe":6,"minecraft:wooden_pickaxe":1,"minecraft:raw_gold":5,"simplyswords:iron_greathammer":1},"minecraft:killed":{"minecraft:cave_spider":1,"irons_spellbooks:cryomancer":3,"alexsmobs:shoebill":1,"minecraft:cod":3,"irons_spellbooks:summoned_polar_bear":3,"iceandfire:stymphalian_bird":3,"minecraft:skeleton":147,"irons_spellbooks:apothecarist":3,"alexsmobs:centipede_head":2,"iceandfire:dread_scuttler":4,"irons_spellbooks:archevoker":1,"minecraft:cat":1,"minecraft:magma_cube":5,"alexsmobs:seal":11,"minecraft:pillager":7,"irons_spellbooks:summoned_vex":2,"minecraft:donkey":2,"minecraft:zombie":206,"iceandfire:dread_ghoul":24,"iceandfire:lightning_dragon":4,"iceandfire:sea_serpent":2,"minecraft:cow":9,"minecraft:evoker":1,"minecraft:vindicator":1,"minecraft:horse":5,"iceandfire:dread_knight":11,"iceandfire:cyclops":2,"minecraft:rabbit":1,"alexsmobs:catfish":5,"alexsmobs:gelada_monkey":2,"alexsmobs:crocodile":1,"iceandfire:ice_dragon":4,"alexsmobs:hummingbird":2,"knightquest:eldknight":1,"minecraft:zombified_piglin":1,"minecraft:witch":1,"minecraft:spider":54,"block_factorys_bosses:flaming_skeleton_guard_sword":12,"minecraft:silverfish":11,"minecraft:piglin_brute":2,"alexsmobs:kangaroo":9,"artifacts:mimic":5,"minecraft:piglin":11,"minecraft:pig":2,"alexsmobs:grizzly_bear":1,"minecraft:zombie_villager":1,"irons_spellbooks:necromancer":4,"minecraft:creeper":31,"alexsmobs:crimson_mosquito":12,"minecraft:sheep":11,"minecraft:stray":9,"alexsmobs:fly":2,"knightquest:gremlin":11,"minecraft:vex":3,"irons_spellbooks:summoned_zombie":15,"block_factorys_bosses:flaming_skeleton_guard_fireball":2,"minecraft:slime":14,"iceandfire:dread_thrall":39,"iceandfire:fire_dragon":4,"minecraft:drowned":1,"alexsmobs:bison":1,"iceandfire:deathworm":1,"knightquest:eldbomb":3,"iceandfire:troll":1,"minecraft:bat":1,"minecraft:hoglin":9,"minecraft:squid":1,"alexsmobs:moose":1,"alexsmobs:crow":1,"minecraft:wither_skeleton":3},"minecraft:picked_up":{"iceandfire:dread_stone_bricks":3,"minecraft:iron_chestplate":1,"minecraft:chainmail_boots":5,"irons_spellbooks:affinity_ring":3,"minecraft:smithing_table":1,"minecraft:stone_slab":1,"minecraft:oak_stairs":1,"irons_spellbooks:holy_rune":1,"minecraft:enchanted_book":4,"minecraft:brewing_stand":2,"minecraft:amethyst_block":22,"iceandfire:manuscript":64,"minecraft:polished_blackstone_brick_stairs":3,"minecraft:string":62,"block_factorys_bosses:wall_torch":1,"create:limestone":2,"minecraft:cooked_salmon":5,"simplyswords:diamond_scythe":6,"minecraft:gold_nugget":48,"minecraft:cobbled_deepslate":85,"minecraft:spruce_planks":5,"irons_spellbooks:blank_rune":1,"hangglider:hang_glider":3,"minecraft:melon_slice":56,"artifacts:universal_attractor":2,"minecraft:acacia_log":7,"iceandfire:lightning_dragon_flesh":3,"alexsmobs:centipede_leg":2,"minecraft:orange_bed":10,"minecraft:stone_sword":1,"iceandfire:deathworm_chitin_yellow":3,"iceandfire:fire_dragon_heart":4,"minecraft:cyan_terracotta":17,"minecraft:snowball":137,"iceandfire:sapphire_gem":2,"minecraft:magma_block":7,"minecraft:feather":11,"minecraft:cooked_beef":5,"minecraft:flint":3,"alexsmobs:cooked_kangaroo_meat":7,"minecraft:magenta_bed":2,"irons_spellbooks:concentration_amulet":3,"minecraft:lantern":8,"artifacts:shock_pendant":2,"minecraft:purple_carpet":1,"iceandfire:ice_dragon_blood":1,"minecraft:chipped_anvil":1,"minecraft:diamond_helmet":1,"iceandfire:dragonscales_amythest":7,"irons_spellbooks:legendary_ink":6,"irons_spellbooks:frostward_ring":1,"block_factorys_bosses:dragon_bone":18,"iceandfire:dragon_skull_fire":3,"iceandfire:shiny_scales":2,"iceandfire:armor_blue_chestplate":2,"iceandfire:stymphalian_bird_feather":4,"minecraft:dark_oak_log":2,"minecraft:barrel":12,"irons_spellbooks:ice_rune":2,"alexsmobs:kangaroo_hide":10,"iceandfire:lectern":1,"minecraft:writable_book":1,"minecraft:chainmail_helmet":6,"minecraft:bread":31,"iceandfire:troll_leather_forest":6,"alexsmobs:maggot":4,"minecraft:crimson_roots":5,"iceandfire:raw_silver":4,"minecraft:diamond_pickaxe":3,"iceandfire:dragon_skull_lightning":7,"iceandfire:witherbone":2,"irons_spellbooks:tarnished_helmet":1,"gravestone:obituary":25,"block_factorys_bosses:ancient_iron_nugget":1,"iceandfire:sea_serpent_scales_blue":6,"minecraft:cornflower":4,"irons_spellbooks:diamond_spell_book":2,"alexsmobs:cooked_catfish":21,"minecraft:flint_and_steel":1,"create:scorchia":38,"minecraft:white_carpet":3,"minecraft:cracked_stone_bricks":7,"iceandfire:bestiary":1,"minecraft:beef":4,"iceandfire:dread_shard":49,"minecraft:poppy":5,"irons_spellbooks:emerald_stoneplate_ring":4,"minecraft:chest":1,"artifacts:charm_of_sinking":1,"minecraft:redstone":1,"iceandfire:armor_blue_boots":1,"iceandfire:dragon_skull_ice":4,"irons_spellbooks:evocation_rune":1,"minecraft:tnt":6,"minecraft:cooked_cod":1,"minecraft:hay_block":242,"artifacts:pocket_piston":3,"minecraft:gold_ingot":44,"minecraft:totem_of_undying":1,"minecraft:mutton":13,"alexsmobs:kangaroo_meat":3,"minecraft:white_wool":15,"minecraft:oxeye_daisy":4,"minecraft:stripped_oak_log":1,"iceandfire:sea_serpent_fang":8,"minecraft:red_mushroom":1,"minecraft:acacia_wood":4,"minecraft:oak_log":8,"iceandfire:dragonscales_blue":43,"minecraft:paper":92,"minecraft:white_banner":3,"iceandfire:pixie_house_mushroom_red":2,"minecraft:apple":5,"minecraft:stone_bricks":33,"minecraft:stone_pickaxe":1,"minecraft:cobweb":4,"minecraft:glass_bottle":3,"minecraft:iron_sword":1,"iceandfire:copper_nugget":82,"minecraft:smooth_basalt":26,"minecraft:sweet_berries":117,"minecraft:gravel":30,"iceandfire:cyclops_skull":5,"minecraft:spruce_sapling":18,"minecraft:spruce_log":373,"irons_spellbooks:poisonward_ring":1,"minecraft:slime_ball":14,"iceandfire:ice_dragon_flesh":15,"block_factorys_bosses:bone_remains":2,"minecraft:stripped_dark_oak_log":2,"minecraft:ender_pearl":1,"irons_spellbooks:scroll":20,"minecraft:wheat":54,"alexscaves:cave_tablet":16,"minecraft:potion":2,"minecraft:stone_brick_stairs":6,"irons_spellbooks:cast_time_ring":1,"alexsmobs:gazelle_horn":1,"irons_spellbooks:nature_rune":4,"minecraft:iron_leggings":1,"irons_spellbooks:arcane_essence":37,"alexsmobs:blood_sac":12,"block_factorys_bosses:dragon_skull":1,"minecraft:bucket":1,"alexsmobs:cooked_moose_ribs":1,"minecraft:white_tulip":2,"minecraft:cobblestone_slab":2,"minecraft:calcite":11,"minecraft:azalea":2,"minecraft:iron_pickaxe":1,"irons_spellbooks:inscription_table":1,"iceandfire:dragonscales_red":5,"minecraft:iron_boots":1,"minecraft:furnace":8,"minecraft:tipped_arrow":2,"minecraft:stick":29,"minecraft:acacia_fence":1,"iceandfire:dread_sword":2,"block_factorys_bosses:vase":2,"minecraft:torch":8,"iceandfire:pixie_house_mushroom_brown":3,"travelersbackpack:iron_tier_upgrade":1,"iceandfire:dragonscales_white":9,"minecraft:spruce_stairs":2,"minecraft:porkchop":3,"iceandfire:crackled_gravel":2,"iceandfire:lightning_dragon_blood":2,"minecraft:mangrove_stairs":2,"minecraft:rotten_flesh":146,"create:asurine":2,"relics:aqua_walker":1,"minecraft:mangrove_roots":1,"block_factorys_bosses:ancient_iron_ingot":1,"minecraft:obsidian":36,"irons_spellbooks:cooldown_ring":4,"minecraft:cobblestone":457,"minecraft:pink_petals":3,"relics:roller_skates":5,"minecraft:black_bed":2,"minecraft:potato":1,"minecraft:tuff":5,"minecraft:acacia_boat":2,"artifacts:pickaxe_heater":1,"minecraft:dirt":87,"simplyswords:frostfall":17,"irons_spellbooks:hogskin":6,"travelersbackpack:bookshelf":4,"minecraft:bone":182,"minecraft:acacia_planks":6,"minecraft:bow":10,"minecraft:wheat_seeds":204,"iceandfire:armor_amythest_boots":1,"minecraft:raw_gold":9,"minecraft:bell":1,"minecraft:fletching_table":4,"minecraft:bamboo":91,"minecraft:oak_planks":5,"irons_spellbooks:frozen_bone":9,"minecraft:cooked_porkchop":27,"iceandfire:pixie_house_birch":2,"minecraft:sand":26,"minecraft:cyan_bed":40,"simplyswords:iron_greathammer":1,"iceandfire:dragonbone_sword_lightning":4,"minecraft:mossy_cobblestone":2,"minecraft:yellow_carpet":3,"minecraft:spruce_boat":6,"minecraft:diamond":31,"irons_spellbooks:divine_pearl":9,"waystones:waystone":3,"iceandfire:dread_stone_bricks_mossy":1,"iceandfire:dragon_ice":1,"minecraft:cracked_polished_blackstone_bricks":32,"minecraft:crossbow":2,"minecraft:grass":1,"minecraft:emerald":18,"irons_spellbooks:uncommon_ink":2,"minecraft:netherrack":388,"iceandfire:silver_nugget":106,"minecraft:charcoal":17,"minecraft:azure_bluet":20,"minecraft:cooked_rabbit":1,"minecraft:diorite_slab":1,"minecraft:gold_block":14,"minecraft:oak_trapdoor":2,"iceandfire:frozen_stone":2,"minecraft:moss_carpet":3,"minecraft:iron_axe":1,"artifacts:feral_claws":9,"minecraft:item_frame":1,"minecraft:blackstone":54,"minecraft:candle":16,"minecraft:oak_boat":1,"irons_spellbooks:epic_ink":4,"block_factorys_bosses:knight_helmet":1,"minecraft:light_gray_wool":1,"minecraft:sugar_cane":3,"iceandfire:podium_acacia":2,"minecraft:phantom_membrane":4,"relics:drowned_belt":4,"iceandfire:ice_dragon_heart":3,"knightlib:small_essence":117,"minecraft:dark_oak_sapling":1,"minecraft:raw_iron":144,"iceandfire:dragonscales_gray":15,"iceandfire:dragonbone":95,"iceandfire:dragonscales_green":15,"iceandfire:deathworm_chitin_red":1,"minecraft:copper_ingot":7,"minecraft:polished_blackstone_bricks":120,"minecraft:stone_button":7,"minecraft:stone_pressure_plate":2,"minecraft:dark_oak_planks":1,"block_factorys_bosses:prison_door":1,"minecraft:arrow":106,"iceandfire:cyclops_eye":1,"simplyswords:iron_scythe":5,"irons_spellbooks:invisibility_elixir":1,"minecraft:pink_tulip":3,"minecraft:basalt":17,"artifacts:eternal_steak":2,"minecraft:glow_ink_sac":3,"minecraft:leather":38,"simplyswords:iron_claymore":2,"minecraft:chainmail_chestplate":1,"iceandfire:dread_stone_bricks_cracked":5,"minecraft:nether_wart_block":3,"minecraft:cobbled_deepslate_stairs":1,"minecraft:gunpowder":18,"irons_spellbooks:rare_ink":2,"minecraft:cooked_mutton":12,"irons_spellbooks:common_ink":1,"minecraft:iron_ingot":81,"iceandfire:sea_serpent_scales_deepblue":2,"iceandfire:fire_dragon_flesh":13,"minecraft:acacia_sapling":2,"knightlib:great_essence":57,"minecraft:book":7,"minecraft:pumpkin":1,"block_factorys_bosses:tall_vase":1,"minecraft:stone_brick_slab":2,"iceandfire:ash":3,"minecraft:dandelion":7,"minecraft:amethyst_shard":8,"minecraft:blast_furnace":9,"minecraft:white_bed":1,"minecraft:green_carpet":3,"minecraft:mossy_stone_brick_slab":2,"minecraft:spider_eye":17,"block_factorys_bosses:bone_remains_legs":2,"alexsmobs:raw_catfish":18,"simplyswords:gold_halberd":3,"minecraft:chainmail_leggings":3,"minecraft:iron_helmet":1,"minecraft:damaged_anvil":1,"minecraft:black_wool":1,"iceandfire:chared_gravel":1,"minecraft:coal":92,"minecraft:sunflower":10},"minecraft:custom":{"minecraft:interact_with_crafting_table":156,"minecraft:open_barrel":448,"minecraft:eat_cake_slice":3,"minecraft:leave_game":11,"minecraft:time_since_death":4501,"minecraft:damage_blocked_by_shield":1096,"minecraft:play_time":1619457,"minecraft:deaths":40,"minecraft:jump":33006,"minecraft:interact_with_furnace":48,"minecraft:traded_with_villager":35,"minecraft:sleep_in_bed":50,"minecraft:damage_dealt":168188,"waystones:waystone_activated":8,"minecraft:interact_with_smoker":1,"minecraft:interact_with_smithing_table":4,"minecraft:interact_with_anvil":11,"minecraft:sneak_time":20281,"minecraft:interact_with_blast_furnace":38,"minecraft:total_world_time":1619457,"minecraft:tune_noteblock":3,"minecraft:time_since_rest":4632,"minecraft:swim_one_cm":278135,"minecraft:fly_one_cm":6454358,"minecraft:open_chest":274,"minecraft:fall_one_cm":912006,"minecraft:damage_resisted":3044,"minecraft:sprint_one_cm":3257656,"minecraft:drop":2202,"minecraft:talked_to_villager":15,"minecraft:walk_on_water_one_cm":315266,"minecraft:interact_with_loom":1,"minecraft:player_kills":12,"minecraft:crouch_one_cm":45000,"minecraft:mob_kills":847,"minecraft:interact_with_campfire":11,"minecraft:damage_dealt_resisted":48448,"minecraft:climb_one_cm":48920,"minecraft:walk_one_cm":5605871,"minecraft:walk_under_water_one_cm":142116,"minecraft:boat_one_cm":801578,"minecraft:damage_taken":42793,"minecraft:damage_absorbed":600},"minecraft:killed_by":{"alexsmobs:crocodile":1,"minecraft:player":6},"minecraft:crafted":{"minecraft:chain":3,"minecraft:glass":24,"minecraft:diamond_helmet":1,"minecraft:diamond_leggings":1,"travelersbackpack:bookshelf":3,"minecraft:emerald":38,"simplyswords:iron_claymore":1,"travelersbackpack:standard":4,"minecraft:campfire":1,"iceandfire:armor_gray_chestplate":1,"minecraft:iron_pickaxe":4,"minecraft:gold_ingot":29,"hangglider:glider_framework":4,"minecraft:iron_nugget":36,"iceandfire:armor_amythest_helmet":1,"hangglider:glider_wing":4,"minecraft:spruce_fence":6,"travelersbackpack:blank_upgrade":4,"travelersbackpack:gold_tier_upgrade":2,"travelersbackpack:white_sleeping_bag":2,"minecraft:stone_pickaxe":1,"minecraft:diamond_boots":1,"minecraft:spruce_boat":3,"minecraft:dark_oak_planks":8,"minecraft:wheat":1526,"iceandfire:dragonbone_sword":1,"simplyswords:iron_chakram":1,"simplyswords:iron_halberd":1,"minecraft:enchanted_book":5,"simplyswords:iron_greathammer":2,"iceandfire:armor_white_leggings":1,"minecraft:iron_leggings":2,"block_factorys_bosses:dragon_bones_chestplate":1,"irons_spellbooks:diamond_spell_book":1,"minecraft:oak_planks":24,"iceandfire:armor_blue_helmet":2,"hangglider:hang_glider":2,"irons_spellbooks:iron_spell_book":1,"block_factorys_bosses:dragon_bones_leggings":1,"minecraft:iron_boots":3,"iceandfire:dragonbone_sword_lightning":1,"minecraft:chest":3,"iceandfire:armor_blue_boots":1,"minecraft:stone_hoe":1,"travelersbackpack:iron_tier_upgrade":1,"minecraft:crafting_table":30,"minecraft:spruce_planks":834,"minecraft:wooden_pickaxe":2,"minecraft:iron_helmet":3,"simplyswords:iron_scythe":3,"minecraft:iron_chestplate":3,"iceandfire:armor_blue_leggings":1,"minecraft:diamond_pickaxe":1,"minecraft:shield":2,"minecraft:stick":1100,"minecraft:iron_ingot":144,"minecraft:stone_sword":2,"irons_spellbooks:magic_cloth":2,"iceandfire:armor_gray_leggings":1,"iceandfire:armor_blue_chestplate":2,"minecraft:furnace":7,"minecraft:flint_and_steel":2,"minecraft:iron_axe":2,"minecraft:iron_hoe":1,"travelersbackpack:diamond_tier_upgrade":1,"travelersbackpack:backpack_tank":4,"iceandfire:tide_trident":1,"alexsmobs:cooked_kangaroo_meat":3,"minecraft:cooked_salmon":17,"minecraft:bucket":1,"minecraft:stone_axe":1,"minecraft:acacia_boat":1,"minecraft:bread":510,"minecraft:acacia_planks":28,"minecraft:torch":36,"iceandfire:armor_green_boots":1,"minecraft:diamond_chestplate":1},"minecraft:used":{"minecraft:chest":1,"minecraft:rotten_flesh":4,"minecraft:acacia_sapling":1,"minecraft:spruce_boat":6,"simplyswords:iron_scythe":623,"minecraft:sweet_berries":108,"minecraft:cooked_cod":1,"minecraft:furnace":13,"block_factorys_bosses:vase":1,"minecraft:damaged_anvil":1,"minecraft:wooden_pickaxe":38,"artifacts:eternal_steak":2,"minecraft:golden_apple":10,"minecraft:sand":2,"block_factorys_bosses:enhanced_shield":2,"minecraft:blast_furnace":4,"simplyswords:frostfall":1493,"minecraft:smithing_table":1,"minecraft:oak_boat":1,"minecraft:stone_sword":2,"minecraft:cooked_salmon":21,"minecraft:netherrack":44,"minecraft:orange_bed":10,"minecraft:torch":20,"minecraft:chipped_anvil":1,"simplyswords:diamond_scythe":622,"minecraft:iron_axe":406,"minecraft:totem_of_undying":1,"minecraft:barrel":12,"iceandfire:armor_blue_boots":1,"minecraft:acacia_wood":2,"minecraft:cobbled_deepslate":25,"minecraft:acacia_planks":4,"alexsmobs:cooked_catfish":21,"minecraft:water_bucket":23,"minecraft:fletching_table":4,"iceandfire:dragon_skull_lightning":2,"minecraft:polished_blackstone_bricks":38,"minecraft:tnt":1,"minecraft:crafting_table":30,"minecraft:white_bed":1,"minecraft:campfire":1,"minecraft:diamond_pickaxe":794,"travelersbackpack:bookshelf":62,"minecraft:sunflower":5,"minecraft:iron_pickaxe":688,"iceandfire:cyclops_skull":5,"minecraft:cobblestone":271,"minecraft:potion":7,"travelersbackpack:standard":4,"minecraft:porkchop":1,"minecraft:cooked_porkchop":21,"minecraft:dandelion":1,"minecraft:shield":65,"minecraft:iron_sword":1,"minecraft:tuff":5,"minecraft:obsidian":34,"iceandfire:cannoli":1,"minecraft:item_frame":1,"minecraft:magma_block":7,"minecraft:hay_block":1,"minecraft:dark_oak_sapling":1,"minecraft:diamond_boots":1,"minecraft:stone_pickaxe":41,"minecraft:ender_pearl":8,"minecraft:white_wool":1,"minecraft:golden_hoe":34,"simplyswords:iron_chakram":1,"iceandfire:dragonbone_sword_lightning":70,"minecraft:black_bed":2,"simplyswords:iron_greathammer":222,"waystones:waystone":3,"minecraft:melon_slice":21,"minecraft:bread":413,"minecraft:cyan_bed":34,"minecraft:string":2,"iceandfire:ice_dragon_flesh":6,"minecraft:gravel":22,"alexsmobs:cooked_moose_ribs":1,"minecraft:cooked_rabbit":1,"minecraft:cobweb":11,"minecraft:experience_bottle":8,"minecraft:flint_and_steel":2,"minecraft:spruce_planks":70,"minecraft:stone_hoe":32,"minecraft:dirt":4,"minecraft:white_carpet":3,"minecraft:spruce_stairs":1,"minecraft:diamond_helmet":1,"alexsmobs:cooked_kangaroo_meat":8,"minecraft:spruce_fence":6,"minecraft:iron_hoe":89,"minecraft:light_gray_wool":1,"minecraft:golden_carrot":6,"minecraft:stone_pressure_plate":1,"minecraft:cooked_beef":2,"minecraft:iron_leggings":1,"minecraft:cooked_mutton":9,"minecraft:acacia_boat":2,"iceandfire:fire_dragon_flesh":4,"minecraft:magenta_bed":1,"minecraft:apple":8,"iceandfire:ash":1,"minecraft:stone_axe":2,"minecraft:bucket":22},"minecraft:mined":{"minecraft:dark_oak_planks":1,"minecraft:white_bed":1,"minecraft:obsidian":28,"minecraft:acacia_log":6,"minecraft:spawner":6,"minecraft:polished_blackstone_bricks":69,"minecraft:tall_seagrass":1,"minecraft:magma_block":7,"minecraft:fire":3,"minecraft:barrel":13,"minecraft:fletching_table":5,"iceandfire:gold_pile":1,"minecraft:dirt_path":2,"minecraft:green_carpet":1,"iceandfire:dread_stone_bricks_cracked":5,"minecraft:orange_bed":9,"minecraft:crimson_nylium":15,"minecraft:amethyst_cluster":1,"minecraft:powder_snow":1,"minecraft:torch":3,"minecraft:blast_furnace":8,"minecraft:melon":13,"minecraft:cyan_bed":37,"minecraft:sugar_cane":2,"minecraft:damaged_anvil":1,"minecraft:amethyst_block":11,"minecraft:jungle_wood":1,"minecraft:wheat":4,"minecraft:magenta_bed":2,"minecraft:black_bed":1,"minecraft:stone_brick_stairs":6,"minecraft:grass":163,"minecraft:smooth_basalt":26,"minecraft:deepslate":46,"minecraft:yellow_terracotta":1,"iceandfire:silver_ore":4,"minecraft:mossy_cobblestone":2,"iceandfire:pixie_house_birch":2,"minecraft:dark_oak_log":2,"minecraft:crimson_roots":7,"minecraft:acacia_wood":4,"iceandfire:chared_gravel":1,"minecraft:cobblestone_slab":2,"minecraft:vine":19,"minecraft:glass_pane":5,"minecraft:stone_brick_slab":2,"iceandfire:pixie_house_mushroom_brown":3,"minecraft:campfire":1,"minecraft:tall_grass":9,"minecraft:spruce_log":357,"minecraft:birch_leaves":1,"minecraft:gravel":37,"minecraft:cobweb":14,"minecraft:acacia_planks":1,"minecraft:stone_bricks":26,"minecraft:chipped_anvil":1,"minecraft:gold_ore":4,"minecraft:fern":13,"minecraft:infested_stone":2,"minecraft:large_amethyst_bud":2,"minecraft:spruce_planks":3,"block_factorys_bosses:prison_door":1,"minecraft:cobbled_deepslate_stairs":1,"minecraft:mossy_stone_brick_slab":2,"minecraft:sculk_vein":1,"minecraft:brewing_stand":1,"minecraft:budding_amethyst":3,"minecraft:grass_block":24,"minecraft:cracked_polished_blackstone_bricks":31,"iceandfire:lectern":1,"minecraft:iron_ore":103,"minecraft:azure_bluet":3,"create:asurine":2,"minecraft:azalea_leaves":1,"minecraft:cyan_terracotta":17,"minecraft:blackstone":37,"iceandfire:dragon_ice_spikes":1,"minecraft:calcite":11,"minecraft:poppy":1,"minecraft:chest":1,"minecraft:cobblestone":24,"minecraft:oak_planks":3,"minecraft:seagrass":1,"minecraft:nether_wart_block":3,"minecraft:tnt":3,"iceandfire:dread_stone_bricks_mossy":1,"minecraft:oak_log":7,"block_factorys_bosses:vase":1,"minecraft:acacia_fence":1,"minecraft:sand":26,"minecraft:dirt":10,"minecraft:netherrack":364,"iceandfire:dread_stone_bricks":4,"minecraft:oak_leaves":18,"minecraft:tuff":5,"minecraft:dark_oak_leaves":6,"minecraft:deepslate_diamond_ore":28,"minecraft:candle":3,"minecraft:mangrove_roots":1,"gravestone:gravestone":28,"iceandfire:frozen_stone":1,"minecraft:spruce_leaves":49,"minecraft:rooted_dirt":1,"minecraft:large_fern":10,"minecraft:hay_block":243,"minecraft:diorite_slab":1,"minecraft:oak_trapdoor":2,"minecraft:spruce_sapling":1,"minecraft:furnace":7,"create:scorchia":39,"minecraft:gold_block":8,"minecraft:bookshelf":1,"minecraft:deepslate_iron_ore":36,"minecraft:stripped_oak_log":1,"minecraft:packed_ice":2,"minecraft:stone":324,"minecraft:podzol":1,"minecraft:stripped_dark_oak_log":2,"minecraft:basalt":18,"minecraft:andesite_slab":1,"minecraft:polished_blackstone_brick_stairs":1,"minecraft:sculk":2,"minecraft:spruce_stairs":2,"minecraft:sweet_berry_bush":49,"minecraft:ice":3,"iceandfire:pixie_house_mushroom_red":2,"minecraft:coal_ore":68,"minecraft:cracked_stone_bricks":7}},"DataVersion":3465}